odoo/addons/mgmtsystem_nonconformity/README.rst
odoo/addons/mgmtsystem_nonconformity/__init__.py
odoo/addons/mgmtsystem_nonconformity/__manifest__.py
odoo/addons/mgmtsystem_nonconformity/data/mail_message_subtype.xml
odoo/addons/mgmtsystem_nonconformity/data/mgmtsystem_nonconformity_cause.xml
odoo/addons/mgmtsystem_nonconformity/data/mgmtsystem_nonconformity_origin.xml
odoo/addons/mgmtsystem_nonconformity/data/mgmtsystem_nonconformity_severity.xml
odoo/addons/mgmtsystem_nonconformity/data/mgmtsystem_nonconformity_stage.xml
odoo/addons/mgmtsystem_nonconformity/data/sequence.xml
odoo/addons/mgmtsystem_nonconformity/demo/mgmtsystem_nonconformity.xml
odoo/addons/mgmtsystem_nonconformity/demo/mgmtsystem_nonconformity_cause.xml
odoo/addons/mgmtsystem_nonconformity/demo/mgmtsystem_nonconformity_origin.xml
odoo/addons/mgmtsystem_nonconformity/i18n/am.po
odoo/addons/mgmtsystem_nonconformity/i18n/ca.po
odoo/addons/mgmtsystem_nonconformity/i18n/de.po
odoo/addons/mgmtsystem_nonconformity/i18n/el_GR.po
odoo/addons/mgmtsystem_nonconformity/i18n/es.po
odoo/addons/mgmtsystem_nonconformity/i18n/es_CO.po
odoo/addons/mgmtsystem_nonconformity/i18n/es_ES.po
odoo/addons/mgmtsystem_nonconformity/i18n/fi.po
odoo/addons/mgmtsystem_nonconformity/i18n/fr.po
odoo/addons/mgmtsystem_nonconformity/i18n/gl.po
odoo/addons/mgmtsystem_nonconformity/i18n/hr_HR.po
odoo/addons/mgmtsystem_nonconformity/i18n/hu.po
odoo/addons/mgmtsystem_nonconformity/i18n/it.po
odoo/addons/mgmtsystem_nonconformity/i18n/lv.po
odoo/addons/mgmtsystem_nonconformity/i18n/mgmtsystem_nonconformity.pot
odoo/addons/mgmtsystem_nonconformity/i18n/nb.po
odoo/addons/mgmtsystem_nonconformity/i18n/nl.po
odoo/addons/mgmtsystem_nonconformity/i18n/nl_NL.po
odoo/addons/mgmtsystem_nonconformity/i18n/nn.po
odoo/addons/mgmtsystem_nonconformity/i18n/pt.po
odoo/addons/mgmtsystem_nonconformity/i18n/pt_BR.po
odoo/addons/mgmtsystem_nonconformity/i18n/pt_PT.po
odoo/addons/mgmtsystem_nonconformity/i18n/sl.po
odoo14_addon_mgmtsystem_nonconformity-14.0.2.1.0.dist-info/METADATA
odoo14_addon_mgmtsystem_nonconformity-14.0.2.1.0.dist-info/WHEEL
odoo14_addon_mgmtsystem_nonconformity-14.0.2.1.0.dist-info/top_level.txt
odoo14_addon_mgmtsystem_nonconformity-14.0.2.1.0.dist-info/RECORD
